apiiif/__about__.py
apiiif/__init__.py
apiiif/factory.py
apiiif/resource_properties.py
apiiif/resource_types.py
apiiif-0.3.3.dist-info/METADATA
apiiif-0.3.3.dist-info/WHEEL
apiiif-0.3.3.dist-info/licenses/LICENSE.txt
apiiif-0.3.3.dist-info/RECORD
