Metadata-Version: 2.4
Name: apiiif
Version: 0.3.3
Project-URL: Documentation, https://github.com/d-flood/apiiif#readme
Project-URL: Issues, https://github.com/d-flood/apiiif/issues
Project-URL: Source, https://github.com/d-flood/apiiif
Author-email: David Flood <d-flood@users.noreply.github.com>
License-Expression: MIT
License-File: LICENSE.txt
Classifier: Development Status :: 4 - Beta
Classifier: Programming Language :: Python
Classifier: Programming Language :: Python :: 3.10
Classifier: Programming Language :: Python :: 3.11
Classifier: Programming Language :: Python :: 3.12
Classifier: Programming Language :: Python :: 3.13
Classifier: Programming Language :: Python :: Implementation :: CPython
Classifier: Programming Language :: Python :: Implementation :: PyPy
Requires-Python: >=3.10
Requires-Dist: pydantic==2.11.4
